multi_channel_pytorch/__init__.py
multi_channel_pytorch/injection.py
multi_channel_pytorch/multify.py
multi_channel_pytorch/utils.py
multi_channel_pytorch-0.2.1.dist-info/LICENSE
multi_channel_pytorch-0.2.1.dist-info/METADATA
multi_channel_pytorch-0.2.1.dist-info/WHEEL
multi_channel_pytorch-0.2.1.dist-info/RECORD
